flightcheck/__init__.py
flightcheck/flightcheck.cpython-37m-darwin.so
flightcheck/config/get_account_audit_records.cfg
flightcheck/config/get_certificate_checking_status.cfg
flightcheck/config/get_cloudn_backup_config.cfg
flightcheck/config/get_controller_apache_version.cfg
flightcheck/config/get_controller_security_group_management_status.cfg
flightcheck/config/get_gateway_info.cfg
flightcheck/config/get_latest_release_version.cfg
flightcheck/config/get_remote_syslog_status.cfg
flightcheck/config/is_controller_saml_login_enabled.cfg
flightcheck/config/list_account_users.cfg
flightcheck/config/list_accounts.cfg
flightcheck/config/list_all_security_patches.cfg
flightcheck/config/list_all_software_patches.cfg
flightcheck/config/list_extended_vpc_peer.cfg
flightcheck/config/list_firenet.cfg
flightcheck/config/list_gateways.cfg
flightcheck/config/list_peer_vpc_pairs.cfg
flightcheck/config/list_site2cloud.cfg
flightcheck/config/list_spoke_gws.cfg
flightcheck/config/list_transit_gws.cfg
flightcheck/config/list_version_info.cfg
flightcheck/config/list_vpcs.cfg
flightcheck/config/show_firenet_detail.cfg
flightcheck/config/flightlog/get_jumbo_frame_status.cfg
flightcheck/config/flightlog/get_transit_gateway_route_table.cfg
flightcheck/config/flightlog/list_aviatrix_transit_gateways.cfg
flightcheck/config/flightlog/list_custom_vpcs.cfg
flightcheck/config/flightlog/list_gateway_upgrade_status.cfg
flightcheck/config/flightlog/list_gateways.cfg
flightcheck/config/flightlog/list_transit_firenet_spoke_policies.cfg
flightcheck/config/flightlog/list_transit_gws.cfg
aviatrix_flightcheck-0.1.1.dist-info/METADATA
aviatrix_flightcheck-0.1.1.dist-info/WHEEL
aviatrix_flightcheck-0.1.1.dist-info/entry_points.txt
aviatrix_flightcheck-0.1.1.dist-info/top_level.txt
aviatrix_flightcheck-0.1.1.dist-info/RECORD
