Metadata-Version: 2.1
Name: aviatrix-flightcheck
Version: 0.1.1
Summary: Aviatrix FlightCheck
Author: Aviatrix Automation
Author-email: aviatrix-ps-dev@aviatrix.com
License: UNKNOWN
Project-URL: Changelog, https://github.com/aviatrix-automation/flightcheck/blob/master/CHANGELOG.rst
Project-URL: Issue Tracker, https://github.com/aviatrix-automation/flightcheck/issues
Platform: UNKNOWN
Classifier: Development Status :: 4 - Beta
Classifier: Environment :: Console
Classifier: Intended Audience :: Developers
Classifier: Operating System :: MacOS :: MacOS X
Classifier: Operating System :: Microsoft :: Windows
Classifier: Operating System :: POSIX :: Linux
Classifier: Programming Language :: Cython
Classifier: Programming Language :: Python
Classifier: Programming Language :: Python :: 3
Classifier: Programming Language :: Python :: 3 :: Only
Classifier: Programming Language :: Python :: 3.7
Classifier: Programming Language :: Python :: 3.8
Classifier: Programming Language :: Python :: 3.9
Classifier: Programming Language :: Python :: Implementation :: CPython
Classifier: Topic :: Utilities
Requires-Python: >=3.7
Requires-Dist: requests
